// class version 55.0 (55)
// access flags 0x21
public class org/sourceflow/gradient/sensor/test/MonitoringSut {

  // compiled from: MonitoringSut.java

  @Lorg/sourceflow/gradient/annotation/InModelingUniverse;()

  // access flags 0xA
  private static I staticField

  // access flags 0x1
  public I field

  // access flags 0x1
  public <init>(I)V
   L0
    LINENUMBER 16 L0
    ALOAD 0
    INVOKESPECIAL java/lang/Object.<init> ()V
   L1
    LINENUMBER 17 L1
    ALOAD 0
    ILOAD 1
    PUTFIELD org/sourceflow/gradient/sensor/test/MonitoringSut.field : I
   L2
    LINENUMBER 18 L2
    RETURN
   L3
    LOCALVARIABLE this Lorg/sourceflow/gradient/sensor/test/MonitoringSut; L0 L3 0
    LOCALVARIABLE param I L0 L3 1
    MAXSTACK = 2
    MAXLOCALS = 2

  // access flags 0x1
  public getField()I
    SIPUSH 264
    INVOKESTATIC org/sourceflow/gradient/sensor/monitoring/ByteCodeFacade.frame (I)J
    LSTORE 1
   L0
    LINENUMBER 21 L0
    ALOAD 0
    GETFIELD org/sourceflow/gradient/sensor/test/MonitoringSut.field : I
    SIPUSH 264
    SIPUSH 287
    LLOAD 1
    INVOKESTATIC org/sourceflow/gradient/sensor/monitoring/ByteCodeFacade.read (IIIJ)I
    SIPUSH 264
    LLOAD 1
    INVOKESTATIC org/sourceflow/gradient/sensor/monitoring/ByteCodeFacade.returns (IIJ)I
    IRETURN
   L1
    LOCALVARIABLE this Lorg/sourceflow/gradient/sensor/test/MonitoringSut; L0 L1 0
    MAXSTACK = 5
    MAXLOCALS = 3

  // access flags 0x1
  public incField()I
    SIPUSH 265
    INVOKESTATIC org/sourceflow/gradient/sensor/monitoring/ByteCodeFacade.frame (I)J
    LSTORE 1
   L0
    LINENUMBER 25 L0
    ALOAD 0
    DUP
    GETFIELD org/sourceflow/gradient/sensor/test/MonitoringSut.field : I
    SIPUSH 265
    SIPUSH 287
    LLOAD 1
    INVOKESTATIC org/sourceflow/gradient/sensor/monitoring/ByteCodeFacade.read (IIIJ)I
    ICONST_1
    IADD
    DUP_X1
    SIPUSH 265
    SIPUSH 287
    LLOAD 1
    INVOKESTATIC org/sourceflow/gradient/sensor/monitoring/ByteCodeFacade.write (IIIJ)I
    PUTFIELD org/sourceflow/gradient/sensor/test/MonitoringSut.field : I
    SIPUSH 265
    LLOAD 1
    INVOKESTATIC org/sourceflow/gradient/sensor/monitoring/ByteCodeFacade.returns (IIJ)I
    IRETURN
   L1
    LOCALVARIABLE this Lorg/sourceflow/gradient/sensor/test/MonitoringSut; L0 L1 0
    MAXSTACK = 7
    MAXLOCALS = 3

  // access flags 0x1
  public addToField(I)I
    SIPUSH 266
    INVOKESTATIC org/sourceflow/gradient/sensor/monitoring/ByteCodeFacade.frame (I)J
    LSTORE 2
    ILOAD 1
    SIPUSH 266
    SIPUSH 267
    LLOAD 2
    INVOKESTATIC org/sourceflow/gradient/sensor/monitoring/ByteCodeFacade.receiveV (IIIJ)V
   L0
    LINENUMBER 29 L0
    ALOAD 0
    DUP
    GETFIELD org/sourceflow/gradient/sensor/test/MonitoringSut.field : I
    SIPUSH 266
    SIPUSH 287
    LLOAD 2
    INVOKESTATIC org/sourceflow/gradient/sensor/monitoring/ByteCodeFacade.read (IIIJ)I
    ILOAD 1
    IADD
    SIPUSH 266
    SIPUSH 287
    LLOAD 2
    INVOKESTATIC org/sourceflow/gradient/sensor/monitoring/ByteCodeFacade.write (IIIJ)I
    PUTFIELD org/sourceflow/gradient/sensor/test/MonitoringSut.field : I
   L1
    LINENUMBER 30 L1
    ALOAD 0
    INVOKEVIRTUAL org/sourceflow/gradient/sensor/test/MonitoringSut.getField ()I
    SIPUSH 266
    LLOAD 2
    INVOKESTATIC org/sourceflow/gradient/sensor/monitoring/ByteCodeFacade.returns (IIJ)I
    IRETURN
   L2
    LOCALVARIABLE this Lorg/sourceflow/gradient/sensor/test/MonitoringSut; L0 L2 0
    LOCALVARIABLE a I L0 L2 1
    MAXSTACK = 6
    MAXLOCALS = 4

  // access flags 0x1
  public local(I)I
    SIPUSH 268
    INVOKESTATIC org/sourceflow/gradient/sensor/monitoring/ByteCodeFacade.frame (I)J
    LSTORE 2
    ILOAD 1
    SIPUSH 268
    SIPUSH 269
    LLOAD 2
    INVOKESTATIC org/sourceflow/gradient/sensor/monitoring/ByteCodeFacade.receiveV (IIIJ)V
   L0
    LINENUMBER 34 L0
    ILOAD 1
    ICONST_1
    IADD
    ISTORE 4
   L1
    LINENUMBER 35 L1
    ILOAD 4
    SIPUSH 268
    LLOAD 2
    INVOKESTATIC org/sourceflow/gradient/sensor/monitoring/ByteCodeFacade.returns (IIJ)I
    IRETURN
   L2
    LOCALVARIABLE this Lorg/sourceflow/gradient/sensor/test/MonitoringSut; L0 L2 0
    LOCALVARIABLE a I L0 L2 1
    LOCALVARIABLE b I L1 L2 4
    MAXSTACK = 5
    MAXLOCALS = 5

  // access flags 0x1
  public externalExcluded(J)V
   L0
    LINENUMBER 39 L0
    LLOAD 1
    LCONST_1
    LADD
    LSTORE 3
   L1
    LINENUMBER 40 L1
    GETSTATIC java/lang/System.out : Ljava/io/PrintStream;
    LLOAD 3
    INVOKEVIRTUAL java/io/PrintStream.println (J)V
   L2
    LINENUMBER 41 L2
    RETURN
   L3
    LOCALVARIABLE this Lorg/sourceflow/gradient/sensor/test/MonitoringSut; L0 L3 0
    LOCALVARIABLE a J L0 L3 1
    LOCALVARIABLE b J L1 L3 3
    MAXSTACK = 4
    MAXLOCALS = 5

  // access flags 0x1
  public externalIncluded(J)V
   L0
    LINENUMBER 44 L0
    LLOAD 1
    LCONST_1
    LADD
    LCONST_1
    LSUB
    LSTORE 3
   L1
    LINENUMBER 45 L1
    GETSTATIC java/lang/System.out : Ljava/io/PrintStream;
    LLOAD 3
    INVOKEVIRTUAL java/io/PrintStream.print (J)V
   L2
    LINENUMBER 46 L2
    RETURN
   L3
    LOCALVARIABLE this Lorg/sourceflow/gradient/sensor/test/MonitoringSut; L0 L3 0
    LOCALVARIABLE a J L0 L3 1
    LOCALVARIABLE b J L1 L3 3
    MAXSTACK = 4
    MAXLOCALS = 5

  // access flags 0x1
  // signature (Ljava/util/List<Ljava/lang/String;>;)Ljava/util/List<Ljava/lang/String;>;
  // declaration: java.util.List<java.lang.String> stringList(java.util.List<java.lang.String>)
  public stringList(Ljava/util/List;)Ljava/util/List;
    SIPUSH 274
    INVOKESTATIC org/sourceflow/gradient/sensor/monitoring/ByteCodeFacade.frame (I)J
    LSTORE 2
    ALOAD 1
    SIPUSH 274
    SIPUSH 275
    LLOAD 2
    INVOKESTATIC org/sourceflow/gradient/sensor/monitoring/ByteCodeFacade.receiveV (Ljava/lang/Object;IIJ)V
   L0
    LINENUMBER 49 L0
    GETSTATIC java/lang/System.out : Ljava/io/PrintStream;
    ALOAD 1
    INVOKEINTERFACE java/util/List.size ()I (itf)
    INVOKEVIRTUAL java/io/PrintStream.println (I)V
   L1
    LINENUMBER 50 L1
    ALOAD 1
    SIPUSH 274
    LLOAD 2
    INVOKESTATIC org/sourceflow/gradient/sensor/monitoring/ByteCodeFacade.returns (Ljava/lang/Object;IJ)Ljava/lang/Object;
    CHECKCAST java/util/List
    ARETURN
   L2
    LOCALVARIABLE this Lorg/sourceflow/gradient/sensor/test/MonitoringSut; L0 L2 0
    LOCALVARIABLE lst Ljava/util/List; L0 L2 1
    // signature Ljava/util/List<Ljava/lang/String;>;
    // declaration: lst extends java.util.List<java.lang.String>
    MAXSTACK = 5
    MAXLOCALS = 4

  // access flags 0x1
  public stringArray([Ljava/lang/String;)[Ljava/lang/String;
    SIPUSH 276
    INVOKESTATIC org/sourceflow/gradient/sensor/monitoring/ByteCodeFacade.frame (I)J
    LSTORE 2
    ALOAD 1
    SIPUSH 276
    SIPUSH 277
    LLOAD 2
    INVOKESTATIC org/sourceflow/gradient/sensor/monitoring/ByteCodeFacade.receiveV (Ljava/lang/Object;IIJ)V
   L0
    LINENUMBER 54 L0
    GETSTATIC java/lang/System.out : Ljava/io/PrintStream;
    ALOAD 1
    ARRAYLENGTH
    INVOKEVIRTUAL java/io/PrintStream.println (I)V
   L1
    LINENUMBER 55 L1
    ALOAD 1
    SIPUSH 276
    LLOAD 2
    INVOKESTATIC org/sourceflow/gradient/sensor/monitoring/ByteCodeFacade.returns (Ljava/lang/Object;IJ)Ljava/lang/Object;
    CHECKCAST [Ljava/lang/String;
    ARETURN
   L2
    LOCALVARIABLE this Lorg/sourceflow/gradient/sensor/test/MonitoringSut; L0 L2 0
    LOCALVARIABLE lst [Ljava/lang/String; L0 L2 1
    MAXSTACK = 5
    MAXLOCALS = 4

  // access flags 0x1
  // signature (Ljava/util/List<Ljava/lang/Float;>;)Ljava/util/List<Ljava/lang/Float;>;
  // declaration: java.util.List<java.lang.Float> primitiveList(java.util.List<java.lang.Float>)
  public primitiveList(Ljava/util/List;)Ljava/util/List;
    SIPUSH 278
    INVOKESTATIC org/sourceflow/gradient/sensor/monitoring/ByteCodeFacade.frame (I)J
    LSTORE 2
    ALOAD 1
    SIPUSH 278
    SIPUSH 279
    LLOAD 2
    INVOKESTATIC org/sourceflow/gradient/sensor/monitoring/ByteCodeFacade.receiveV (Ljava/lang/Object;IIJ)V
   L0
    LINENUMBER 59 L0
    GETSTATIC java/lang/System.out : Ljava/io/PrintStream;
    ALOAD 1
    INVOKEINTERFACE java/util/List.size ()I (itf)
    INVOKEVIRTUAL java/io/PrintStream.println (I)V
   L1
    LINENUMBER 60 L1
    ALOAD 1
    SIPUSH 278
    LLOAD 2
    INVOKESTATIC org/sourceflow/gradient/sensor/monitoring/ByteCodeFacade.returns (Ljava/lang/Object;IJ)Ljava/lang/Object;
    CHECKCAST java/util/List
    ARETURN
   L2
    LOCALVARIABLE this Lorg/sourceflow/gradient/sensor/test/MonitoringSut; L0 L2 0
    LOCALVARIABLE lst Ljava/util/List; L0 L2 1
    // signature Ljava/util/List<Ljava/lang/Float;>;
    // declaration: lst extends java.util.List<java.lang.Float>
    MAXSTACK = 5
    MAXLOCALS = 4

  // access flags 0x1
  public inheritanceCall()V
   L0
    LINENUMBER 64 L0
    NEW java/io/IOException
    DUP
    INVOKESPECIAL java/io/IOException.<init> ()V
    INVOKEVIRTUAL java/io/IOException.printStackTrace ()V
   L1
    LINENUMBER 65 L1
    RETURN
   L2
    LOCALVARIABLE this Lorg/sourceflow/gradient/sensor/test/MonitoringSut; L0 L2 0
    MAXSTACK = 2
    MAXLOCALS = 1

  // access flags 0x1
  public exception(Ljava/lang/String;)V
    TRYCATCHBLOCK L0 L1 L2 java/lang/Throwable
    TRYCATCHBLOCK L3 L4 L5 java/lang/Throwable
    TRYCATCHBLOCK L6 L7 L8 java/io/IOException
    TRYCATCHBLOCK L6 L7 L9 null
    TRYCATCHBLOCK L8 L10 L9 null
    TRYCATCHBLOCK L9 L11 L9 null
   L6
    LINENUMBER 68 L6
    NEW java/io/FileInputStream
    DUP
    NEW java/io/File
    DUP
    ALOAD 1
    INVOKESPECIAL java/io/File.<init> (Ljava/lang/String;)V
    INVOKESPECIAL java/io/FileInputStream.<init> (Ljava/io/File;)V
    ASTORE 2
   L0
    LINENUMBER 69 L0
    ALOAD 2
    INVOKEVIRTUAL java/io/FileInputStream.available ()I
    POP
   L1
    LINENUMBER 70 L1
    ALOAD 2
    INVOKEVIRTUAL java/io/FileInputStream.close ()V
    GOTO L7
   L2
    LINENUMBER 68 L2
   FRAME FULL [org/sourceflow/gradient/sensor/test/MonitoringSut java/lang/String java/io/FileInputStream] [java/lang/Throwable]
    ASTORE 3
   L3
    ALOAD 2
    INVOKEVIRTUAL java/io/FileInputStream.close ()V
   L4
    GOTO L12
   L5
   FRAME FULL [org/sourceflow/gradient/sensor/test/MonitoringSut java/lang/String java/io/FileInputStream java/lang/Throwable] [java/lang/Throwable]
    ASTORE 4
    ALOAD 3
    ALOAD 4
    INVOKEVIRTUAL java/lang/Throwable.addSuppressed (Ljava/lang/Throwable;)V
   L12
   FRAME FULL [org/sourceflow/gradient/sensor/test/MonitoringSut java/lang/String java/io/FileInputStream java/lang/Throwable] []
    ALOAD 3
    ATHROW
   L7
    LINENUMBER 73 L7
   FRAME FULL [org/sourceflow/gradient/sensor/test/MonitoringSut java/lang/String] []
    GETSTATIC java/lang/System.out : Ljava/io/PrintStream;
    ALOAD 1
    INVOKEVIRTUAL java/io/PrintStream.print (Ljava/lang/String;)V
   L13
    LINENUMBER 74 L13
    GOTO L14
   L8
    LINENUMBER 70 L8
   FRAME FULL [org/sourceflow/gradient/sensor/test/MonitoringSut java/lang/String] [java/io/IOException]
    ASTORE 2
   L15
    LINENUMBER 71 L15
    ALOAD 2
    INVOKEVIRTUAL java/io/IOException.printStackTrace ()V
   L10
    LINENUMBER 73 L10
    GETSTATIC java/lang/System.out : Ljava/io/PrintStream;
    ALOAD 1
    INVOKEVIRTUAL java/io/PrintStream.print (Ljava/lang/String;)V
   L16
    LINENUMBER 74 L16
    GOTO L14
   L9
    LINENUMBER 73 L9
   FRAME FULL [org/sourceflow/gradient/sensor/test/MonitoringSut java/lang/String] [java/lang/Throwable]
    ASTORE 5
   L11
    GETSTATIC java/lang/System.out : Ljava/io/PrintStream;
    ALOAD 1
    INVOKEVIRTUAL java/io/PrintStream.print (Ljava/lang/String;)V
   L17
    LINENUMBER 74 L17
    ALOAD 5
    ATHROW
   L14
    LINENUMBER 75 L14
   FRAME FULL [org/sourceflow/gradient/sensor/test/MonitoringSut java/lang/String] []
    RETURN
   L18
    LOCALVARIABLE f Ljava/io/FileInputStream; L0 L7 2
    LOCALVARIABLE ex Ljava/io/IOException; L15 L10 2
    LOCALVARIABLE this Lorg/sourceflow/gradient/sensor/test/MonitoringSut; L6 L18 0
    LOCALVARIABLE fileName Ljava/lang/String; L6 L18 1
    MAXSTACK = 5
    MAXLOCALS = 6

  // access flags 0x1
  public throwing(Ljava/lang/String;)V
   L0
    LINENUMBER 78 L0
    NEW java/lang/IllegalArgumentException
    DUP
    ALOAD 1
    INVOKESPECIAL java/lang/IllegalArgumentException.<init> (Ljava/lang/String;)V
    ATHROW
   L1
    LOCALVARIABLE this Lorg/sourceflow/gradient/sensor/test/MonitoringSut; L0 L1 0
    LOCALVARIABLE file Ljava/lang/String; L0 L1 1
    MAXSTACK = 3
    MAXLOCALS = 2

  // access flags 0x9
  // signature ()Ljava/util/List<Ljava/lang/Integer;>;
  // declaration: java.util.List<java.lang.Integer> name()
  public static name()Ljava/util/List;
    SIPUSH 285
    INVOKESTATIC org/sourceflow/gradient/sensor/monitoring/ByteCodeFacade.frame (I)J
    LSTORE 0
   L0
    LINENUMBER 82 L0
    NEW java/util/ArrayList
    DUP
    INVOKESPECIAL java/util/ArrayList.<init> ()V
    ASTORE 2
   L1
    LINENUMBER 83 L1
    ALOAD 2
    GETSTATIC org/sourceflow/gradient/sensor/test/MonitoringSut.staticField : I
    SIPUSH 285
    SIPUSH 286
    LLOAD 0
    INVOKESTATIC org/sourceflow/gradient/sensor/monitoring/ByteCodeFacade.read (IIIJ)I
    INVOKESTATIC java/lang/Integer.valueOf (I)Ljava/lang/Integer;
    INVOKEINTERFACE java/util/List.add (Ljava/lang/Object;)Z (itf)
    POP
   L2
    LINENUMBER 84 L2
    ALOAD 2
    SIPUSH 285
    LLOAD 0
    INVOKESTATIC org/sourceflow/gradient/sensor/monitoring/ByteCodeFacade.returns (Ljava/lang/Object;IJ)Ljava/lang/Object;
    CHECKCAST java/util/List
    ARETURN
   L3
    LOCALVARIABLE list Ljava/util/List; L1 L3 2
    // signature Ljava/util/List<Ljava/lang/Integer;>;
    // declaration: list extends java.util.List<java.lang.Integer>
    MAXSTACK = 6
    MAXLOCALS = 3
}
